LICENSE
README.md
setup.py
src/get_crypto_price/__init__.py
src/get_crypto_price/get_crypto_price.py
src/get_crypto_price.egg-info/PKG-INFO
src/get_crypto_price.egg-info/SOURCES.txt
src/get_crypto_price.egg-info/dependency_links.txt
src/get_crypto_price.egg-info/entry_points.txt
src/get_crypto_price.egg-info/not-zip-safe
src/get_crypto_price.egg-info/requires.txt
src/get_crypto_price.egg-info/top_level.txt