Metadata-Version: 2.1
Name: get-crypto-price
Version: 0.1.0
Summary: A library to getting crypto price.
Home-page: https://github.com/onuratakan/get_crypto_price
Author: Onur Atakan ULUSOY
Author-email: atadogan06@gmail.com
License: MIT
Platform: UNKNOWN
Requires-Python: >= 3
License-File: LICENSE
